README.md
setup.cfg
setup.py
src/nlpcleaner/__init__.py
src/nlpcleaner.egg-info/PKG-INFO
src/nlpcleaner.egg-info/SOURCES.txt
src/nlpcleaner.egg-info/dependency_links.txt
src/nlpcleaner.egg-info/not-zip-safe
src/nlpcleaner.egg-info/requires.txt
src/nlpcleaner.egg-info/top_level.txt
src/nlpcleaner/data/nltk/corpora/stopwords/arabic
src/nlpcleaner/data/nltk/corpora/stopwords/azerbaijani
src/nlpcleaner/data/nltk/corpora/stopwords/danish
src/nlpcleaner/data/nltk/corpora/stopwords/dutch
src/nlpcleaner/data/nltk/corpora/stopwords/english
src/nlpcleaner/data/nltk/corpora/stopwords/finnish
src/nlpcleaner/data/nltk/corpora/stopwords/french
src/nlpcleaner/data/nltk/corpora/stopwords/german
src/nlpcleaner/data/nltk/corpora/stopwords/greek
src/nlpcleaner/data/nltk/corpora/stopwords/hungarian
src/nlpcleaner/data/nltk/corpora/stopwords/indonesian
src/nlpcleaner/data/nltk/corpora/stopwords/italian
src/nlpcleaner/data/nltk/corpora/stopwords/kazakh
src/nlpcleaner/data/nltk/corpora/stopwords/nepali
src/nlpcleaner/data/nltk/corpora/stopwords/norwegian
src/nlpcleaner/data/nltk/corpora/stopwords/portuguese
src/nlpcleaner/data/nltk/corpora/stopwords/romanian
src/nlpcleaner/data/nltk/corpora/stopwords/russian
src/nlpcleaner/data/nltk/corpora/stopwords/slovene
src/nlpcleaner/data/nltk/corpora/stopwords/spanish
src/nlpcleaner/data/nltk/corpora/stopwords/swedish
src/nlpcleaner/data/nltk/corpora/stopwords/tajik
src/nlpcleaner/data/nltk/corpora/stopwords/turkish
src/nlpcleaner/data/nltk/corpora/wordnet/LICENSE
src/nlpcleaner/data/nltk/corpora/wordnet/README
src/nlpcleaner/data/nltk/corpora/wordnet/adj.exc
src/nlpcleaner/data/nltk/corpora/wordnet/adv.exc
src/nlpcleaner/data/nltk/corpora/wordnet/citation.bib
src/nlpcleaner/data/nltk/corpora/wordnet/cntlist.rev
src/nlpcleaner/data/nltk/corpora/wordnet/data.adj
src/nlpcleaner/data/nltk/corpora/wordnet/data.adv
src/nlpcleaner/data/nltk/corpora/wordnet/data.noun
src/nlpcleaner/data/nltk/corpora/wordnet/data.verb
src/nlpcleaner/data/nltk/corpora/wordnet/index.adj
src/nlpcleaner/data/nltk/corpora/wordnet/index.adv
src/nlpcleaner/data/nltk/corpora/wordnet/index.noun
src/nlpcleaner/data/nltk/corpora/wordnet/index.sense
src/nlpcleaner/data/nltk/corpora/wordnet/index.verb
