Metadata-Version: 2.1
Name: nlpcleaner
Version: 0.3.1
Summary: Clean and prepare text for modeling with machine learning
Home-page: https://github.com/giovannelli/nlpcleaner
Author: Duccio Giovannelli
Author-email: giovannelli@extendi.it
License: MIT
Platform: UNKNOWN
Classifier: Development Status :: 4 - Beta
Classifier: Intended Audience :: Developers
Classifier: License :: OSI Approved :: MIT License
Classifier: Programming Language :: Python
Classifier: Programming Language :: Python :: 3
Classifier: Programming Language :: Python :: 3.5
Classifier: Programming Language :: Python :: 3.6
Classifier: Programming Language :: Python :: 3.7
Classifier: Programming Language :: Python :: 3.8
